freemocap/__init__.py
freemocap/__main__.py
freemocap/.idea/workspace.xml
freemocap/assets/charuco/charuco_as_groundplane.png
freemocap/assets/charuco/charuco_board_5x3.png
freemocap/assets/charuco/charuco_board_5x3.svg
freemocap/assets/charuco/charuco_board_5x3_annotated.png
freemocap/assets/charuco/charuco_board_7x5.png
freemocap/assets/charuco/charuco_board_7x5.svg
freemocap/assets/charuco/charuco-pdf-tiles/3x5/chauco-tile-3x5.pdf
freemocap/assets/charuco/charuco-pdf-tiles/3x5/how-to-assemble-3x5.pdf
freemocap/assets/charuco/charuco-pdf-tiles/5x7/charuco-tile-5x7.pdf
freemocap/assets/charuco/charuco-pdf-tiles/5x7/how-to-assemble-5x7.pdf
freemocap/assets/logo/freemocap-logo-black-border.svg
freemocap/assets/logo/freemocap-skelly-logo-black-border-transparent-bkgd.png
freemocap/assets/logo/freemocap-skelly-logo-black-border-white-bkgd.png
freemocap/assets/logo/freemocap_skelly_logo.ico
freemocap/assets/logo/skelly-heart-eyes.png
freemocap/assets/logo/skelly-heart-eyes.svg
freemocap/assets/logo/skelly-sweat.png
freemocap/assets/logo/skelly-sweat.svg
freemocap/assets/logo/skelly-this-way-up.png
freemocap/assets/logo/skelly-this-way-up.svg
freemocap/assets/mac_app_files/freemocap.icns
freemocap/assets/mac_app_files/info.plist
freemocap/core_processes/__init__.py
freemocap/core_processes/capture_volume_calibration/__init__.py
freemocap/core_processes/capture_volume_calibration/by_camera_reprojection_filtering.py
freemocap/core_processes/capture_volume_calibration/run_anipose_capture_volume_calibration.py
freemocap/core_processes/capture_volume_calibration/save_3d_data_to_npy.py
freemocap/core_processes/capture_volume_calibration/triangulate_3d_data.py
freemocap/core_processes/capture_volume_calibration/anipose_camera_calibration/__init__.py
freemocap/core_processes/capture_volume_calibration/anipose_camera_calibration/anipose_camera_calibrator.py
freemocap/core_processes/capture_volume_calibration/anipose_camera_calibration/charuco_groundplane_utils.py
freemocap-1.7.4.dist-info/entry_points.txt
freemocap-1.7.4.dist-info/licenses/LICENSE
freemocap-1.7.4.dist-info/WHEEL
freemocap-1.7.4.dist-info/METADATA
freemocap-1.7.4.dist-info/RECORD
