Metadata-Version: 2.4
Name: freemocap
Version: 1.7.4
Summary: A free and open source markerless motion capture system for everyone 💀✨
Keywords: camera,stream,video,image,opencv,skelly,freemocap,motion capture,markerless motion capture,mocap,markerless mocap,markerless,kinematic,animation,3d animation,Blender,Blender3d,synchronization,computer vision
Author: Endurance Idehen, Aaron Cherian, Jonathan Samir Matthis
Author-email: Skelly FreeMoCap <info@freemocap.org>
Requires-Python: >=3.10,<3.13
Classifier: Development Status :: 3 - Alpha
Classifier: License :: OSI Approved :: GNU Affero General Public License v3 or later (AGPLv3+)
Classifier: Intended Audience :: Developers
Classifier: Intended Audience :: Education
Classifier: Intended Audience :: Healthcare Industry
Classifier: Intended Audience :: Science/Research
Classifier: Intended Audience :: End Users/Desktop
Classifier: Intended Audience :: Other Audience
Classifier: Natural Language :: English
Classifier: Operating System :: OS Independent
Classifier: Programming Language :: Python :: 3
Classifier: Programming Language :: Python :: 3.10
Classifier: Programming Language :: Python :: 3.11
Classifier: Programming Language :: Python :: 3.12
Classifier: Topic :: Software Development :: Libraries :: Python Modules
Classifier: Topic :: Utilities
Classifier: Topic :: Multimedia :: Video
Classifier: Topic :: Multimedia :: Video :: Capture
Classifier: Topic :: Multimedia :: Video :: Display
Classifier: Topic :: Scientific/Engineering
Classifier: Topic :: Scientific/Engineering :: Image Processing
Classifier: Topic :: Scientific/Engineering :: Visualization
Classifier: Topic :: Scientific/Engineering :: Human Machine Interfaces
Classifier: Topic :: System :: Hardware
Classifier: Topic :: System :: Hardware :: Universal Serial Bus (USB)
Classifier: Topic :: System :: Hardware :: Universal Serial Bus (USB) :: Video (UVC)
License-File: LICENSE
Requires-Dist: skellycam==2025.09.1097
Requires-Dist: skelly_viewer==2025.04.1028
Requires-Dist: skellyforge==2024.12.1009
Requires-Dist: skelly_synchronize==2025.04.1037
Requires-Dist: skellytracker[all]==2025.10.1024
Requires-Dist: ajc27_freemocap_blender_addon== v2025.11.1038
Requires-Dist: opencv-contrib-python==4.8.*
Requires-Dist: toml==0.10.2
Requires-Dist: aniposelib==0.4.3
Requires-Dist: libsass==0.21.0
Requires-Dist: ipykernel==6.23.1
Requires-Dist: plotly==5.14.1
Requires-Dist: pydantic==2.*
Requires-Dist: PySide6>=6.6, <6.8
Requires-Dist: packaging===23.2
Requires-Dist: black ; extra == "dev"
Requires-Dist: bumpver ; extra == "dev"
Requires-Dist: isort ; extra == "dev"
Requires-Dist: pip-tools ; extra == "dev"
Requires-Dist: pytest ; extra == "dev"
Requires-Dist: pytest-cov ; extra == "dev"
Requires-Dist: flit ; extra == "dev"
Requires-Dist: flake8 ; extra == "dev"
Requires-Dist: flake8-bugbear ; extra == "dev"
Requires-Dist: flake8-bandit ; extra == "dev"
Project-URL: Documentation, https://freemocap.github.io/documentation/
Project-URL: Github, https://github.com/freemocap/freemocap
Project-URL: Homepage, https://freemocap.org
Provides-Extra: dev
